CleanText/__init__.py
CleanText/clean_data.py
cleantext_tn-0.0.7.dist-info/LICENSE
cleantext_tn-0.0.7.dist-info/METADATA
cleantext_tn-0.0.7.dist-info/WHEEL
cleantext_tn-0.0.7.dist-info/top_level.txt
cleantext_tn-0.0.7.dist-info/RECORD
