Metadata-Version: 2.1
Name: cleantext-tn
Version: 0.0.7
Summary: Clean text package
Home-page: https://github.com/minhthu6521/clean-text
Author: Thu Nguyen
Author-email: minhthu6521@gmail.com
License: UNKNOWN
Project-URL: Bug Tracker, https://github.com/minhthu6521/clean-text/issues
Platform: UNKNOWN
Classifier: Programming Language :: Python :: 3
Classifier: License :: OSI Approved :: MIT License
Classifier: Operating System :: OS Independent
Requires-Python: >=3.6
License-File: LICENSE
Requires-Dist: nltk (==3.6.5)
